README.rst
setup.py
sweech.py
sweech_cli.egg-info/PKG-INFO
sweech_cli.egg-info/SOURCES.txt
sweech_cli.egg-info/dependency_links.txt
sweech_cli.egg-info/entry_points.txt
sweech_cli.egg-info/top_level.txt