Metadata-Version: 1.1
Name: sweech-cli
Version: 1.0.1
Summary: A command-line utility to interact with your Android device through the Sweech app
Home-page: https://github.com/alberthier/sweech-cli
Author: Eric ALBER
Author-email: eric.alber@gmail.com
License: MIT
Platform: UNKNOWN
Classifier: Development Status :: 4 - Beta
Classifier: Environment :: Console
Classifier: Intended Audience :: Developers
Classifier: Intended Audience :: Information Technology
Classifier: License :: OSI Approved :: MIT License
Classifier: Operating System :: OS Independent
Classifier: Programming Language :: Python
